{
  "products": [
    {
      "id;": 1,
      "tittle": "MacBook Air",
      "price": 900,
      "image": "assets/images/apple-macbook-pro-13-m1-8gb-256gb-ssd-Ноутбук.jpg",
      "configure" : {
        "chip": "M1",
        "ssd": "256 GB",
        "memory": "8 GB",
        "display": "Retina"
      }
    },

    {
      "id;": 2,
      "tittle": "MacBook Pro",
      "price": 1300,
      "image": "assets/images/apple-macbook-pro-13-m1-8gb-256gb-ssd-Ноутбук.jpg",
      "configure" : {
        "chip": "M1",
        "ssd": "256 GB",
        "memory": "16 GB",
        "display": "Retina"
      }
    },

    {
      "id;": 3,
      "tittle": "MacBook Pro Intel",
      "price": 1000,
      "image": "assets/images/apple-macbook-pro-13-m1-8gb-256gb-ssd-Ноутбук.jpg",
      "configure" : {
        "chip": "Intel",
        "ssd": "256 GB",
        "memory": "16 GB",
        "display": "Retina"
      }
    }

  ]
}
